LICENSE
MANIFEST.in
README.md
setup.cfg
setup.py
Pokie.egg-info/PKG-INFO
Pokie.egg-info/SOURCES.txt
Pokie.egg-info/dependency_links.txt
Pokie.egg-info/entry_points.txt
Pokie.egg-info/not-zip-safe
Pokie.egg-info/requires.txt
Pokie.egg-info/top_level.txt
pokie/__init__.py
pokie/__main__.py
pokie/config.py
pokie/constants.py
pokie/cache/__init__.py
pokie/cache/dummy.py
pokie/cache/memory.py
pokie/cache/redis.py
pokie/cli/__init__.py
pokie/cli/pokie.py
pokie/codegen/__init__.py
pokie/codegen/record.py
pokie/codegen/request.py
pokie/codegen/spec.py
pokie/codegen/template.py
pokie/codegen/textfile.py
pokie/codegen/pg/__init__.py
pokie/codegen/pg/spec.py
pokie/contrib/__init__.py
pokie/contrib/auth/__init__.py
pokie/contrib/auth/constants.py
pokie/contrib/auth/module.py
pokie/contrib/auth/user.py
pokie/contrib/auth/cli/__init__.py
pokie/contrib/auth/cli/acl.py
pokie/contrib/auth/cli/user.py
pokie/contrib/auth/dto/__init__.py
pokie/contrib/auth/dto/acl.py
pokie/contrib/auth/dto/token.py
pokie/contrib/auth/dto/user.py
pokie/contrib/auth/provider/__init__.py
pokie/contrib/auth/provider/session_provider.py
pokie/contrib/auth/provider/token_provider.py
pokie/contrib/auth/repository/__init__.py
pokie/contrib/auth/repository/acl.py
pokie/contrib/auth/repository/token.py
pokie/contrib/auth/repository/user.py
pokie/contrib/auth/service/__init__.py
pokie/contrib/auth/service/acl.py
pokie/contrib/auth/service/user.py
pokie/contrib/auth/sql/001-auth-schema.sql
pokie/contrib/auth/sql/002-auth-token.sql
pokie/contrib/auth/sql/003-jwt.sql
pokie/contrib/auth/view/__init__.py
pokie/contrib/auth/view/account.py
pokie/contrib/base/__init__.py
pokie/contrib/base/constants.py
pokie/contrib/base/module.py
pokie/contrib/base/cli/__init__.py
pokie/contrib/base/cli/base.py
pokie/contrib/base/cli/db.py
pokie/contrib/base/cli/db_codegen.py
pokie/contrib/base/cli/fixture.py
pokie/contrib/base/cli/job.py
pokie/contrib/base/cli/module.py
pokie/contrib/base/cli/pytest.py
pokie/contrib/base/cli/route.py
pokie/contrib/base/cli/tpl_codegen.py
pokie/contrib/base/dto/__init__.py
pokie/contrib/base/dto/records.py
pokie/contrib/base/job/__init__.py
pokie/contrib/base/job/idle.py
