Metadata-Version: 2.4
Name: Pokie
Version: 0.9.5
Summary: A high-level Python REST web framework based on Flask, Rick and RickDb.
Home-page: https://git.oddbit.org/OddBit/pokie
Author: João Pinheiro
License: BSD-3-Clause
Project-URL: Documentation, https://docs.oddbit.org/pokie/
Project-URL: Source, https://git.oddbit.org/OddBit/pokie
Classifier: Environment :: Web Environment
Classifier: Development Status :: 4 - Beta
Classifier: Intended Audience :: Developers
Classifier: License :: OSI Approved :: BSD License
Classifier: Operating System :: OS Independent
Classifier: Programming Language :: Python
Classifier: Programming Language :: Python :: 3.8
Classifier: Programming Language :: Python :: 3.9
Classifier: Programming Language :: Python :: 3.10
Classifier: Programming Language :: Python :: 3.11
Classifier: Programming Language :: Python :: 3.12
Classifier: Programming Language :: Python :: 3.13
Classifier: Programming Language :: Python :: 3.14
Classifier: Topic :: Internet :: WWW/HTTP
Classifier: Topic :: Internet :: WWW/HTTP :: Dynamic Content
Classifier: Topic :: Internet :: WWW/HTTP :: WSGI
Classifier: Topic :: Software Development :: Libraries :: Application Frameworks
Classifier: Topic :: Software Development :: Libraries :: Python Modules
Requires-Python: >=3.10
License-File: LICENSE
Requires-Dist: rick-db>=2.0.2
Requires-Dist: rick>=0.8.0
Requires-Dist: rick-mailer>=1.1.1
Requires-Dist: Flask>=3.1.0
Requires-Dist: Werkzeug
Requires-Dist: Flask-Login
Requires-Dist: iso8601>=2.1.0
Requires-Dist: setuptools>=75.6.0
Requires-Dist: tabulate>=0.9.0
Requires-Dist: pyhumps>=3.8.0
Requires-Dist: redis>=5.2.1
Dynamic: license-file
